kaht/__init__.py
kaht/base.py
kaht/config.py
kaht/data.py
kaht/data_module.py
kaht/logger.py
kaht/metrics.py
kaht/model.py
kaht/optim.py
kaht/trainer.py
kaht/utils.py
kaht/wrapper.py
kaht-1.0.0.dist-info/LICENSE
kaht-1.0.0.dist-info/METADATA
kaht-1.0.0.dist-info/WHEEL
kaht-1.0.0.dist-info/top_level.txt
kaht-1.0.0.dist-info/RECORD
