Metadata-Version: 2.1
Name: kaht
Version: 1.0.0
Summary: Simple Lightning Module
Home-page: UNKNOWN
Author: gawainx
Author-email: liangyi@bupt.edu.cn
License: UNKNOWN
Platform: UNKNOWN
Classifier: Programming Language :: Python :: 3.9
Classifier: License :: OSI Approved :: GNU General Public License v3 (GPLv3)
Classifier: Operating System :: OS Independent
Requires-Dist: typed-argument-parser
Requires-Dist: torch
